sphinx_toml/__init__.py
sphinx_toml/models.py
sphinx_toml-0.0.4.dist-info/LICENSE
sphinx_toml-0.0.4.dist-info/WHEEL
sphinx_toml-0.0.4.dist-info/METADATA
sphinx_toml-0.0.4.dist-info/RECORD
