Metadata-Version: 2.1
Name: sphinx_toml
Version: 0.0.4
Summary: Minimal package to load data from a sphinx.toml file next to a conf.py file.
Author-email: Matthias Bussonnier <bussonniermatthias@gmail.com>
Requires-Python: >=3.10
Classifier: License :: OSI Approved :: MIT License
Requires-Dist: tomli ; python_version<'3.11'
Requires-Dist: intersphinx_registry
Requires-Dist: pydantic
Project-URL: Home, https://github.com/Carreau/sphinx_toml
